pywhip/__init__.py
pywhip/cli.py
pywhip/pywhip.py
pywhip/reporters.py
pywhip/validators.py
pywhip/static/template.html
pywhip-0.3.4.dist-info/AUTHORS.rst
pywhip-0.3.4.dist-info/LICENSE
pywhip-0.3.4.dist-info/METADATA
pywhip-0.3.4.dist-info/WHEEL
pywhip-0.3.4.dist-info/entry_points.txt
pywhip-0.3.4.dist-info/top_level.txt
pywhip-0.3.4.dist-info/RECORD
