Metadata-Version: 2.1
Name: pywhip
Version: 0.3.4
Summary: Python package to validate data against whip specifications
Home-page: https://github.com/inbo/pywhip
Author: Stijn Van Hoey
Author-email: stijn.vanhoey@gmail.com
License: MIT license
Keywords: pywhip,whip,Darwin_Core_Archive,data validation
Classifier: Development Status :: 2 - Pre-Alpha
Classifier: Intended Audience :: Developers
Classifier: License :: OSI Approved :: MIT License
Classifier: Natural Language :: English
Classifier: Programming Language :: Python :: 2
Classifier: Programming Language :: Python :: 2.7
Classifier: Programming Language :: Python :: 3
Classifier: Programming Language :: Python :: 3.4
Classifier: Programming Language :: Python :: 3.5
Classifier: Programming Language :: Python :: 3.6
Classifier: Programming Language :: Python :: 3.8
Classifier: Programming Language :: Python :: 3.9
Classifier: Programming Language :: Python :: 3.10
License-File: LICENSE
License-File: AUTHORS.rst
Requires-Dist: Click (>=6.0)
Requires-Dist: python-dwca-reader (==0.13.0)
Requires-Dist: cerberus (==1.3.4)
Requires-Dist: pyaml (==17.12.1)
Requires-Dist: rfc3987 (==1.3.7)
Requires-Dist: python-dateutil (==2.7.2)
Requires-Dist: jinja2
